realtime_asr/__init__.py
realtime_asr/audio.py
realtime_asr/client.py
realtime_asr/types.py
realtime_asr/utils.py
realtime_asr_sdk-0.1.2.dist-info/licenses/LICENSE
realtime_asr_sdk-0.1.2.dist-info/METADATA
realtime_asr_sdk-0.1.2.dist-info/WHEEL
realtime_asr_sdk-0.1.2.dist-info/top_level.txt
realtime_asr_sdk-0.1.2.dist-info/RECORD
