Metadata-Version: 2.4
Name: realtime-asr-sdk
Version: 0.1.2
Summary: Python SDK for real-time speech transcription via WebSocket
Home-page: https://github.com/inccleo/realtime-asr-sdk
Author: Leon
Author-email: 962055298@qq.com
Project-URL: Bug Reports, https://github.com/inccleo/realtime-asr-sdk/issues
Project-URL: Source, https://github.com/inccleo/realtime-asr-sdk
Keywords: speech recognition asr websocket realtime transcription
Classifier: Development Status :: 3 - Alpha
Classifier: Intended Audience :: Developers
Classifier: Topic :: Multimedia :: Sound/Audio :: Speech
Classifier: License :: OSI Approved :: MIT License
Classifier: Programming Language :: Python :: 3
Classifier: Programming Language :: Python :: 3.8
Classifier: Programming Language :: Python :: 3.9
Classifier: Programming Language :: Python :: 3.10
Classifier: Programming Language :: Python :: 3.11
Classifier: Programming Language :: Python :: 3.12
Requires-Python: >=3.8
License-File: LICENSE
Requires-Dist: websocket-client>=1.6.0
Requires-Dist: numpy>=1.24.0
Provides-Extra: audio
Requires-Dist: PyAudio>=0.2.13; extra == "audio"
Provides-Extra: dev
Requires-Dist: pytest>=7.0.0; extra == "dev"
Requires-Dist: black>=23.0.0; extra == "dev"
Requires-Dist: flake8>=6.0.0; extra == "dev"
Requires-Dist: mypy>=1.0.0; extra == "dev"
Dynamic: author
Dynamic: author-email
Dynamic: classifier
Dynamic: description
Dynamic: description-content-type
Dynamic: home-page
Dynamic: keywords
Dynamic: license-file
Dynamic: project-url
Dynamic: provides-extra
Dynamic: requires-dist
Dynamic: requires-python
Dynamic: summary
